Workbook

Sheet README
B2: Kirana Store Reorder & Wastage Tracker
B4: Project Objective
B5: A small kirana (grocery) store owner cannot see, at a glance, which products are about to run out of stock or which categories are losing the most money to wastage (spoilage, damage, expiry). This workbook turns raw daily stock data into a live dashboard that answers both questions automatically.
B7: Sheets in this Workbook
B8: - Dashboard - KPI cards, Top 10 products chart, wastage % by category chart.
B9: - Raw_Data - 43 products, 6 categories, input data (blue font) and calculated columns (black font).
B10: - Category_Summary - SUMIFS-based rollup of sales, wastage and wastage % by category.
B12: Key Formulas Used
B13: - Closing Stock: =Opening Stock + Purchased Qty - Sold Qty - Wastage Qty
B14: - Reorder Status: =IF(Closing Stock < Reorder Level, "Reorder Now", "OK")
B15: - Wastage %: =IFERROR(Wastage Qty / (Sold Qty + Wastage Qty), 0)
B16: - Total Sales Value: =Sold Qty * Selling Price
... B27: Product, price and quantity data is simulated for portfolio/practice purposes (not from a real store). Structure and formula logic reflect how a real kirana store's inventory sheet would be built.

Sheet Dashboard
B2: Kirana Store Reorder & Wastage Dashboard
B3: Inventory, sales and wastage snapshot across 43 products in 6 categories
B5: Total Revenue | D5: Total Wastage Cost | F5: Overall Wastage % | H5: Products to Reorder
B6: =SUM(Raw_Data!O2:O44) -> 1079244.7 | D6: =SUM(Raw_Data!P2:P44) -> 53446.52 | F6: =SUM(Raw_Data!I2:I44)/(SUM(Raw_Data!H2:H44)+SUM(Raw_Data!I2:I44)) -> 0.063987203 | H6: =COUNTIF(Raw_Data!L2:L44,"Reorder Now") -> 21
B10: Top 10 Products by Sales Value | F10: Products Needing Reorder
B11: Rank | C11: Product Name | D11: Sales Value (Rs) | F11: Product Name | G11: Closing Stock | H11: Reorder Level
B12: 1 | C12: =INDEX(Raw_Data!$B$2:$B$44,MATCH(B12,Raw_Data!$Q$2:$Q$44,0)) -> Namkeen Mix 500g | D12: =INDEX(Raw_Data!$O$2:$O$44,MATCH(B12,Raw_Data!$Q$2:$Q$44,0)) -> 67372.2 | F12: See 'Raw_Data' sheet, column L (Reorder Status). Filter that column to 'Reorder Now' to see the exact list. Count of items needing reorder is shown in the KPI card above.
B13: 2 | C13: =INDEX(Raw_Data!$B$2:$B$44,MATCH(B13,Raw_Data!$Q$2:$Q$44,0)) -> Hair Oil 200ml | D13: =INDEX(Raw_Data!$O$2:$O$44,MATCH(B13,Raw_Data!$Q$2:$Q$44,0)) -> 55829.3
B14: 3 | C14: =INDEX(Raw_Data!$B$2:$B$44,MATCH(B14,Raw_Data!$Q$2:$Q$44,0)) -> Tea Powder 250g | D14: =INDEX(Raw_Data!$O$2:$O$44,MATCH(B14,Raw_Data!$Q$2:$Q$44,0)) -> 53844.21
B15: 4 | C15: =INDEX(Raw_Data!$B$2:$B$44,MATCH(B15,Raw_Data!$Q$2:$Q$44,0)) -> Energy Drink 250ml | D15: =INDEX(Raw_Data!$O$2:$O$44,MATCH(B15,Raw_Data!$Q$2:$Q$44,0)) -> 51074.24
B16: 5 | C16: =INDEX(Raw_Data!$B$2:$B$44,MATCH(B16,Raw_Data!$Q$2:$Q$44,0)) -> Floor Cleaner 1L | D16: =INDEX(Raw_Data!$O$2:$O$44,MATCH(B16,Raw_Data!$Q$2:$Q$44,0)) -> 49332.48
B17: 6 | C17: =INDEX(Raw_Data!$B$2:$B$44,MATCH(B17,Raw_Data!$Q$2:$Q$44,0)) -> Sev 200g | D17: =INDEX(Raw_Data!$O$2:$O$44,MATCH(B17,Raw_Data!$Q$2:$Q$44,0)) -> 47573.75
B18: 7 | C18: =INDEX(Raw_Data!$B$2:$B$44,MATCH(B18,Raw_Data!$Q$2:$Q$44,0)) -> Razor Pack | D18: =INDEX(Raw_Data!$O$2:$O$44,MATCH(B18,Raw_Data!$Q$2:$Q$44,0)) -> 46663.78
B19: 8 | C19: =INDEX(Raw_Data!$B$2:$B$44,MATCH(B19,Raw_Data!$Q$2:$Q$44,0)) -> Potato Chips 100g | D19: =INDEX(Raw_Data!$O$2:$O$44,MATCH(B19,Raw_Data!$Q$2:$Q$44,0)) -> 42666.78
B20: 9 | C20: =INDEX(Raw_Data!$B$2:$B$44,MATCH(B20,Raw_Data!$Q$2:$Q$44,0)) -> Detergent Powder 1kg | D20: =INDEX(Raw_Data!$O$2:$O$44,MATCH(B20,Raw_Data!$Q$2:$Q$44,0)) -> 36277.6
B21: 10 | C21: =INDEX(Raw_Data!$B$2:$B$44,MATCH(B21,Raw_Data!$Q$2:$Q$44,0)) -> Wheat Flour 5kg | D21: =INDEX(Raw_Data!$O$2:$O$44,MATCH(B21,Raw_Data!$Q$2:$Q$44,0)) -> 34979.1

Sheet Raw_Data
A1: Product ID | B1: Product Name | C1: Category | D1: Purchase Price (Rs) | E1: Selling Price (Rs) | F1: Opening Stock | G1: Purchased Qty | H1: Sold Qty | I1: Wastage Qty | J1: Closing Stock | K1: Reorder Level | L1: Reorder Status | M1: Wastage % | N1: Profit per Unit (Rs) | O1: Total Sales Value (Rs) | P1: Total Wastage Value (Rs) | Q1: Sales Rank
A2: 1 | B2: Toned Milk 500ml | C2: Dairy | D2: 229.21 | E2: 264.74 | F2: 55 | G2: 61 | H2: 64 | I2: 11 | J2: =F2+G2-H2-I2 -> 41 | K2: 36 | L2: =IF(J2<K2,"Reorder Now","OK") -> OK | M2: =IFERROR(I2/(H2+I2),0) -> 0.14666667 | N2: =E2-D2 -> 35.53 | O2: =H2*E2 -> 16943.36 | P2: =I2*D2 -> 2521.31 | Q2: =RANK(O2,$O$2:$O$44,0) -> 27
A3: 2 | B3: Full Cream Milk 1L | C3: Dairy | D3: 263.12 | E3: 331.29 | F3: 95 | G3: 84 | H3: 100 | I3: 14 | J3: =F3+G3-H3-I3 -> 65 | K3: 21 | L3: =IF(J3<K3,"Reorder Now","OK") -> OK | M3: =IFERROR(I3/(H3+I3),0) -> 0.12280702 | N3: =E3-D3 -> 68.17 | O3: =H3*E3 -> 33129 | P3: =I3*D3 -> 3683.68 | Q3: =RANK(O3,$O$2:$O$44,0) -> 13
A4: 3 | B4: Curd 400g | C4: Dairy | D4: 92.94 | E4: 118.07 | F4: 91 | G4: 55 | H4: 117 | I4: 22 | J4: =F4+G4-H4-I4 -> 7 | K4: 32 | L4: =IF(J4<K4,"Reorder Now","OK") -> Reorder Now | M4: =IFERROR(I4/(H4+I4),0) -> 0.15827338 | N4: =E4-D4 -> 25.13 | O4: =H4*E4 -> 13814.19 | P4: =I4*D4 -> 2044.68 | Q4: =RANK(O4,$O$2:$O$44,0) -> 29
A5: 4 | B5: Paneer 200g | C5: Dairy | D5: 155.54 | E5: 192.84 | F5: 55 | G5: 133 | H5: 142 | I5: 31 | J5: =F5+G5-H5-I5 -> 15 | K5: 40 | L5: =IF(J5<K5,"Reorder Now","OK") -> Reorder Now | M5: =IFERROR(I5/(H5+I5),0) -> 0.17919075 | N5: =E5-D5 -> 37.3 | O5: =H5*E5 -> 27383.28 | P5: =I5*D5 -> 4821.74 | Q5: =RANK(O5,$O$2:$O$44,0) -> 18
A6: 5 | B6: Butter 100g | C6: Dairy | D6: 68.49 | E6: 84.55 | F6: 55 | G6: 49 | H6: 73 | I6: 10 | J6: =F6+G6-H6-I6 -> 21 | K6: 18 | L6: =IF(J6<K6,"Reorder Now","OK") -> OK | M6: =IFERROR(I6/(H6+I6),0) -> 0.12048193 | N6: =E6-D6 -> 16.06 | O6: =H6*E6 -> 6172.15 | P6: =I6*D6 -> 684.9 | Q6: =RANK(O6,$O$2:$O$44,0) -> 38
A7: 6 | B7: Cheese Slices 200g | C7: Dairy | D7: 46.07 | E7: 53.87 | F7: 64 | G7: 107 | H7: 90 | I7: 18 | J7: =F7+G7-H7-I7 -> 63 | K7: 38 | L7: =IF(J7<K7,"Reorder Now","OK") -> OK | M7: =IFERROR(I7/(H7+I7),0) -> 0.16666667 | N7: =E7-D7 -> 7.8 | O7: =H7*E7 -> 4848.3 | P7: =I7*D7 -> 829.26 | Q7: =RANK(O7,$O$2:$O$44,0) -> 39
A8: 7 | B8: Ghee 500ml | C8: Dairy | D8: 168.91 | E8: 198.46 | F8: 68 | G8: 40 | H8: 77 | I8: 14 | J8: =F8+G8-H8-I8 -> 17 | K8: 33 | L8: =IF(J8<K8,"Reorder Now","OK") -> Reorder Now | M8: =IFERROR(I8/(H8+I8),0) -> 0.15384615 | N8: =E8-D8 -> 29.55 | O8: =H8*E8 -> 15281.42 | P8: =I8*D8 -> 2364.74 | Q8: =RANK(O8,$O$2:$O$44,0) -> 28
A9: 8 | B9: Aloo Bhujia 200g | C9: Snacks & Namkeen | D9: 79.42 | E9: 92.44 | F9: 104 | G9: 59 | H9: 91 | I9: 9 | J9: =F9+G9-H9-I9 -> 63 | K9: 22 | L9: =IF(J9<K9,"Reorder Now","OK") -> OK | M9: =IFERROR(I9/(H9+I9),0) -> 0.09 | N9: =E9-D9 -> 13.02 | O9: =H9*E9 -> 8412.04 | P9: =I9*D9 -> 714.78 | Q9: =RANK(O9,$O$2:$O$44,0) -> 36
A10: 9 | B10: Potato Chips 100g | C10: Snacks & Namkeen | D10: 305.27 | E10: 374.27 | F10: 78 | G10: 111 | H10: 114 | I10: 11 | J10: =F10+G10-H10-I10 -> 64 | K10: 26 | L10: =IF(J10<K10,"Reorder Now","OK") -> OK | M10: =IFERROR(I10/(H10+I10),0) -> 0.088 | N10: =E10-D10 -> 69 | O10: =H10*E10 -> 42666.78 | P10: =I10*D10 -> 3357.97 | Q10: =RANK(O10,$O$2:$O$44,0) -> 8
A11: 10 | B11: Mixture 250g | C11: Snacks & Namkeen | D11: 134.02 | E11: 172.09 | F11: 109 | G11: 149 | H11: 138 | I11: 13 | J11: =F11+G11-H11-I11 -> 107 | K11: 34 | L11: =IF(J11<K11,"Reorder Now","OK") -> OK | M11: =IFERROR(I11/(H11+I11),0) -> 0.086092715 | N11: =E11-D11 -> 38.07 | O11: =H11*E11 -> 23748.42 | P11: =I11*D11 -> 1742.26 | Q11: =RANK(O11,$O$2:$O$44,0) -> 22
A12: 11 | B12: Banana Chips 150g | C12: Snacks & Namkeen | D12: 227.72 | E12: 286.2 | F12: 51 | G12: 50 | H12: 67 | I12: 3 | J12: =F12+G12-H12-I12 -> 31 | K12: 35 | L12: =IF(J12<K12,"Reorder Now","OK") -> Reorder Now | M12: =IFERROR(I12/(H12+I12),0) -> 0.042857143 | N12: =E12-D12 -> 58.48 | O12: =H12*E12 -> 19175.4 | P12: =I12*D12 -> 683.16 | Q12: =RANK(O12,$O$2:$O$44,0) -> 26
A13: 12 | B13: Salted Peanuts 200g | C13: Snacks & Namkeen | D13: 245.53 | E13: 293.14 | F13: 61 | G13: 137 | H13: 106 | I13: 11 | J13: =F13+G13-H13-I13 -> 81 | K13: 22 | L13: =IF(J13<K13,"Reorder Now","OK") -> OK | M13: =IFERROR(I13/(H13+I13),0) -> 0.094017094 | N13: =E13-D13 -> 47.61 | O13: =H13*E13 -> 31072.84 | P13: =I13*D13 -> 2700.83 | Q13: =RANK(O13,$O$2:$O$44,0) -> 14
... A44: 43 | B44: Garbage Bags Pack | C44: Household Items | D44: 214.34 | E44: 275.44 | F44: 50 | G44: 81 | H44: 121 | I44: 2 | J44: =F44+G44-H44-I44 -> 8 | K44: 33 | L44: =IF(J44<K44,"Reorder Now","OK") -> Reorder Now | M44: =IFERROR(I44/(H44+I44),0) -> 0.016260163 | N44: =E44-D44 -> 61.1 | O44: =H44*E44 -> 33328.24 | P44: =I44*D44 -> 428.68 | Q44: =RANK(O44,$O$2:$O$44,0) -> 12

Sheet Category_Summary
A1: Category | B1: Total Sold Qty | C1: Total Wastage Qty | D1: Total Sales Value (Rs) | E1: Total Wastage Value (Rs) | F1: Wastage %
A2: Dairy | B2: =SUMIFS(Raw_Data!$H$2:$H$44,Raw_Data!$C$2:$C$44,A2) -> 663 | C2: =SUMIFS(Raw_Data!$I$2:$I$44,Raw_Data!$C$2:$C$44,A2) -> 120 | D2: =SUMIFS(Raw_Data!$O$2:$O$44,Raw_Data!$C$2:$C$44,A2) -> 117571.7 | E2: =SUMIFS(Raw_Data!$P$2:$P$44,Raw_Data!$C$2:$C$44,A2) -> 16950.31 | F2: =IFERROR(C2/(B2+C2),0) -> 0.1532567
A3: Snacks & Namkeen | B3: =SUMIFS(Raw_Data!$H$2:$H$44,Raw_Data!$C$2:$C$44,A3) -> 821 | C3: =SUMIFS(Raw_Data!$I$2:$I$44,Raw_Data!$C$2:$C$44,A3) -> 54 | D3: =SUMIFS(Raw_Data!$O$2:$O$44,Raw_Data!$C$2:$C$44,A3) -> 240021.43 | E3: =SUMIFS(Raw_Data!$P$2:$P$44,Raw_Data!$C$2:$C$44,A3) -> 11340.78 | F3: =IFERROR(C3/(B3+C3),0) -> 0.061714286
A4: Beverages | B4: =SUMIFS(Raw_Data!$H$2:$H$44,Raw_Data!$C$2:$C$44,A4) -> 904 | C4: =SUMIFS(Raw_Data!$I$2:$I$44,Raw_Data!$C$2:$C$44,A4) -> 44 | D4: =SUMIFS(Raw_Data!$O$2:$O$44,Raw_Data!$C$2:$C$44,A4) -> 153831.61 | E4: =SUMIFS(Raw_Data!$P$2:$P$44,Raw_Data!$C$2:$C$44,A4) -> 5647.53 | F4: =IFERROR(C4/(B4+C4),0) -> 0.046413502
A5: Grocery & Staples | B5: =SUMIFS(Raw_Data!$H$2:$H$44,Raw_Data!$C$2:$C$44,A5) -> 808 | C5: =SUMIFS(Raw_Data!$I$2:$I$44,Raw_Data!$C$2:$C$44,A5) -> 42 | D5: =SUMIFS(Raw_Data!$O$2:$O$44,Raw_Data!$C$2:$C$44,A5) -> 141758.72 | E5: =SUMIFS(Raw_Data!$P$2:$P$44,Raw_Data!$C$2:$C$44,A5) -> 6025.84 | F5: =IFERROR(C5/(B5+C5),0) -> 0.049411765
A6: Personal Care | B6: =SUMIFS(Raw_Data!$H$2:$H$44,Raw_Data!$C$2:$C$44,A6) -> 886 | C6: =SUMIFS(Raw_Data!$I$2:$I$44,Raw_Data!$C$2:$C$44,A6) -> 43 | D6: =SUMIFS(Raw_Data!$O$2:$O$44,Raw_Data!$C$2:$C$44,A6) -> 207809.5 | E6: =SUMIFS(Raw_Data!$P$2:$P$44,Raw_Data!$C$2:$C$44,A6) -> 8465.41 | F6: =IFERROR(C6/(B6+C6),0) -> 0.046286329
A7: Household Items | B7: =SUMIFS(Raw_Data!$H$2:$H$44,Raw_Data!$C$2:$C$44,A7) -> 599 | C7: =SUMIFS(Raw_Data!$I$2:$I$44,Raw_Data!$C$2:$C$44,A7) -> 17 | D7: =SUMIFS(Raw_Data!$O$2:$O$44,Raw_Data!$C$2:$C$44,A7) -> 218251.75 | E7: =SUMIFS(Raw_Data!$P$2:$P$44,Raw_Data!$C$2:$C$44,A7) -> 5016.65 | F7: =IFERROR(C7/(B7+C7),0) -> 0.027597403
A8: TOTAL | B8: =SUM(B2:B7) -> 4681 | C8: =SUM(C2:C7) -> 320 | D8: =SUM(D2:D7) -> 1079244.7 | E8: =SUM(E2:E7) -> 53446.52 | F8: =IFERROR(C8/(B8+C8),0) -> 0.063987203
